create_folders.py
down_path.py
fileaway.py
header.py
move_files.py
fileaway-0.0.1.dist-info/METADATA
fileaway-0.0.1.dist-info/WHEEL
fileaway-0.0.1.dist-info/entry_points.txt
fileaway-0.0.1.dist-info/top_level.txt
fileaway-0.0.1.dist-info/RECORD
