Metadata-Version: 2.1
Name: fileaway
Version: 0.0.1
Summary: A nifty tool to sort your messy folders
Home-page: https://github.com/jgyasu/fileaway
Author: Jigyasu
Author-email: jigyasu@outlook.in
Project-URL: Bug Tracker, https://github.com/jgyasu/fileaway/issues
Classifier: Programming Language :: Python :: 3
Classifier: License :: OSI Approved :: MIT License
Classifier: Operating System :: OS Independent
Requires-Python: >=3.6
Requires-Dist: termcolor
